stepwright/__init__.py
stepwright/executor.py
stepwright/helpers.py
stepwright/parser.py
stepwright/scraper.py
stepwright/scraper_parser.py
stepwright/step_types.py
stepwright-0.1.3.dist-info/licenses/LICENSE
stepwright-0.1.3.dist-info/METADATA
stepwright-0.1.3.dist-info/WHEEL
stepwright-0.1.3.dist-info/top_level.txt
stepwright-0.1.3.dist-info/RECORD
