Metadata-Version: 2.4
Name: stepwright
Version: 0.1.3
Summary: A powerful web scraping library built with Playwright that provides a declarative, step-by-step approach to web automation and data extraction
Home-page: https://github.com/lablnet/stepwright
Author: Muhammad Umer Farooq
Author-email: Muhammad Umer Farooq <umer@lablnet.com>
License: MIT
Project-URL: Homepage, https://github.com/lablnet/stepwright
Project-URL: Documentation, https://github.com/lablnet/stepwright#readme
Project-URL: Repository, https://github.com/lablnet/stepwright
Project-URL: Bug Tracker, https://github.com/lablnet/stepwright/issues
Keywords: web scraping,playwright,automation,data extraction,web automation
Classifier: Development Status :: 4 - Beta
Classifier: Intended Audience :: Developers
Classifier: License :: OSI Approved :: MIT License
Classifier: Programming Language :: Python :: 3
Classifier: Programming Language :: Python :: 3.8
Classifier: Programming Language :: Python :: 3.9
Classifier: Programming Language :: Python :: 3.10
Classifier: Programming Language :: Python :: 3.11
Classifier: Programming Language :: Python :: 3.12
Classifier: Topic :: Software Development :: Libraries :: Python Modules
Classifier: Topic :: Internet :: WWW/HTTP
Classifier: Topic :: Software Development :: Testing
Requires-Python: >=3.8
License-File: LICENSE
Requires-Dist: playwright>=1.40.0
Provides-Extra: dev
Requires-Dist: pytest>=8.0.0; extra == "dev"
Requires-Dist: pytest-asyncio>=0.21.0; extra == "dev"
Requires-Dist: pytest-cov>=4.1.0; extra == "dev"
Requires-Dist: black>=23.0.0; extra == "dev"
Requires-Dist: flake8>=6.0.0; extra == "dev"
Requires-Dist: mypy>=1.0.0; extra == "dev"
Dynamic: author
Dynamic: home-page
Dynamic: license-file
Dynamic: requires-python
